konverter/__init__.py
konverter/__main__.py
konverter/utils/__init__.py
konverter/utils/general/__init__.py
konverter/utils/konverter_support.py
konverter/utils/model_attributes.py
keras_konverter-0.2.5.dist-info/entry_points.txt
keras_konverter-0.2.5.dist-info/LICENSE
keras_konverter-0.2.5.dist-info/WHEEL
keras_konverter-0.2.5.dist-info/METADATA
keras_konverter-0.2.5.dist-info/RECORD
