Metadata-Version: 2.1
Name: keras-konverter
Version: 0.2.5
Summary: A tool to convert simple Keras models to pure Python + NumPy
Home-page: https://github.com/ShaneSmiskol/Konverter
License: MIT
Author: Shane Smiskol
Author-email: shane@smiskol.com
Requires-Python: >=3.6,<4.0
Classifier: License :: OSI Approved :: MIT License
Classifier: Programming Language :: Python :: 3
Classifier: Programming Language :: Python :: 3.6
Classifier: Programming Language :: Python :: 3.7
Classifier: Programming Language :: Python :: 3.8
Classifier: Programming Language :: Python :: 3.9
Requires-Dist: numpy (>=1.18.3,<1.19.0)
Project-URL: Repository, https://github.com/ShaneSmiskol/Konverter
